isoviz-0.0.3.dist-info/RECORD
isoviz-0.0.3.dist-info/LICENSE
isoviz-0.0.3.dist-info/WHEEL
isoviz-0.0.3.dist-info/entry_points.txt
isoviz-0.0.3.dist-info/top_level.txt
isoviz-0.0.3.dist-info/METADATA
isoformvisualizer/isoformvisualizer.pyx
isoformvisualizer/__init__.py
isoformvisualizer/isoformvisualizer.py
isoformvisualizer/isoformvisualizer.c
isoformvisualizer/isoformvisualizer.pypy310-pp73-darwin.so
isoformvisualizer/isoviz.py
